infi.dnssimple-0.0.7-py2.7-nspkg.pth
infi/dnssimple/__init__.py
infi/dnssimple/__version__.py
infi/dnssimple/scripts/__init__.py
infi/dnssimple/scripts/ddns.py
infi.dnssimple-0.0.7.dist-info/METADATA
infi.dnssimple-0.0.7.dist-info/WHEEL
infi.dnssimple-0.0.7.dist-info/entry_points.txt
infi.dnssimple-0.0.7.dist-info/namespace_packages.txt
infi.dnssimple-0.0.7.dist-info/top_level.txt
infi.dnssimple-0.0.7.dist-info/RECORD
